hashy/__init__.py
hashy/__version__.py
hashy/bytes.py
hashy/cache.py
hashy/dls_hash.py
hashy/file_hash.py
hashy/py.typed
hashy/string_hash.py
hashy-0.11.0.dist-info/licenses/LICENSE
hashy-0.11.0.dist-info/licenses/LICENSE.txt
hashy-0.11.0.dist-info/METADATA
hashy-0.11.0.dist-info/WHEEL
hashy-0.11.0.dist-info/top_level.txt
hashy-0.11.0.dist-info/RECORD
