Metadata-Version: 2.4
Name: hashy
Version: 0.11.0
Summary: simple hash library for string, file, dict, set and list
Home-page: https://github.com/jamesabel/hashy
Download-URL: https://github.com/jamesabel/hashy
Author: abel
Author-email: j@abel.co
License: MIT License
Keywords: hash
License-File: LICENSE
License-File: LICENSE.txt
Requires-Dist: platformdirs
Requires-Dist: sqlitedict
Dynamic: author
Dynamic: author-email
Dynamic: description
Dynamic: description-content-type
Dynamic: download-url
Dynamic: home-page
Dynamic: keywords
Dynamic: license
Dynamic: license-file
Dynamic: requires-dist
Dynamic: summary
